parstdex/__init__.py
parstdex/marker_extractor.py
parstdex/settings.py
parstdex/utils/__init__.py
parstdex/utils/const.py
parstdex/utils/deprecation.py
parstdex/utils/normalizer.py
parstdex/utils/pattern_to_regex.py
parstdex/utils/regex_tool.py
parstdex/utils/spans.py
parstdex/utils/tokenizer.py
parstdex/utils/pattern_units/adv/ADD.txt
parstdex/utils/pattern_units/adv/ADUQ.txt
parstdex/utils/pattern_units/adv/EVE.txt
parstdex/utils/pattern_units/adv/PAV.txt
parstdex/utils/pattern_units/adv/PEV.txt
parstdex/utils/pattern_units/adv/PLACE.txt
parstdex/utils/pattern_units/adv/POV.txt
parstdex/utils/pattern_units/adv/UNIT.txt
parstdex/utils/pattern_units/ax/CJ.txt
parstdex/utils/pattern_units/ax/NXT.txt
parstdex/utils/pattern_units/ax/PF.txt
parstdex/utils/pattern_units/ax/PRV.txt
parstdex/utils/pattern_units/date/CT.txt
parstdex/utils/pattern_units/date/DN.txt
parstdex/utils/pattern_units/date/DU.txt
parstdex/utils/pattern_units/date/MNTH.txt
parstdex/utils/pattern_units/date/MNTHNOMEY.txt
parstdex/utils/pattern_units/date/RD.txt
parstdex/utils/pattern_units/date/RY.txt
parstdex/utils/pattern_units/date/SSN.txt
parstdex/utils/pattern_units/date/UNQ.txt
parstdex/utils/pattern_units/date/WD.txt
parstdex/utils/pattern_units/time/APM.txt
parstdex/utils/pattern_units/time/DP.txt
parstdex/utils/pattern_units/time/HR.txt
parstdex/utils/pattern_units/time/MIN.txt
parstdex/utils/pattern_units/time/TU.txt
parstdex/utils/patterns/Adversarial.txt
parstdex/utils/patterns/Date.txt
parstdex/utils/patterns/Space.txt
parstdex/utils/patterns/Time.txt
parstdex/utils/special_words/words.txt
tests/__init__.py
tests/data.json
tests/test_parstdex.py
parstdex-1.3.1.dist-info/LICENSE
parstdex-1.3.1.dist-info/METADATA
parstdex-1.3.1.dist-info/WHEEL
parstdex-1.3.1.dist-info/top_level.txt
parstdex-1.3.1.dist-info/RECORD
