Metadata-Version: 2.1
Name: parstdex
Version: 1.3.1
Summary: Persian time and date marker extractor
Home-page: https://github.com/kargaranamir/parstdex
Author: Amir Hossein Kargaran, Sajad Mirzababaei
Author-email: kargaranamir@gmail.com, ss.mirzababaei@gmail.com
License: UNKNOWN
Platform: UNKNOWN
Classifier: Topic :: Text Processing
Classifier: Natural Language :: Persian
Classifier: Programming Language :: Python :: 3.6
Classifier: Programming Language :: Python :: 3.7
Classifier: Programming Language :: Python :: 3.8
Classifier: License :: OSI Approved :: MIT License
Requires-Dist: pytextspan (~=0.5.0)
Requires-Dist: numpy (>=1.12)
